tha/__init__.py
tha/ascii_lines.py
tha/cardinals.py
tha/currency.py
tha/datetime.py
tha/decimals.py
tha/hashtags.py
tha/license_plate.py
tha/normalize.py
tha/ordinals.py
tha/parenthesis.py
tha/phone_numbers.py
tha/punctuations.py
tha/quotings.py
tha/repeater.py
tha/strings.py
tha/urls.py
tha/verbatim.py
tha-0.1.4.dist-info/LICENSE
tha-0.1.4.dist-info/METADATA
tha-0.1.4.dist-info/WHEEL
tha-0.1.4.dist-info/top_level.txt
tha-0.1.4.dist-info/RECORD
