Metadata-Version: 2.1
Name: tha
Version: 0.1.4
Summary: A Khmer Text Normalization and Verbalization Toolkit.
Home-page: https://github.com/seanghay/tha
Author: Seanghay Yath
Author-email: seanghay.dev@gmail.com
License: Apache License 2.0
Classifier: Programming Language :: Python :: 3
Classifier: Operating System :: OS Independent
Classifier: Intended Audience :: Developers
Classifier: Natural Language :: English
Requires-Python: >3.5
License-File: LICENSE
Requires-Dist: urlextract
Requires-Dist: phonenumbers
Requires-Dist: regex
Requires-Dist: ftfy
